LICENSE
README.md
pyproject.toml
setup.py
src/proname/__init__.py
src/proname/dlt.py
src/proname/test_01.py
src/proname.egg-info/PKG-INFO
src/proname.egg-info/SOURCES.txt
src/proname.egg-info/dependency_links.txt
src/proname.egg-info/top_level.txt
src/proname/include/VnHardwareConf.dll