Metadata-Version: 2.1
Name: proname
Version: 1.0.11
Summary: first test package
Home-page: https://www.baidu.com
Author: ZZL
Author-email: test01@163.com
Requires-Python: >=3.6
License-File: LICENSE
